r00notify/__init__.py
r00notify/helpers/__init__.py
r00notify/helpers/constants.py
r00notify/modules/__init__.py
r00notify/modules/telega.py
r00notify/modules/interfaces/__init__.py
r00notify/modules/interfaces/isender.py
r00notify-0.1.1.dist-info/METADATA
r00notify-0.1.1.dist-info/WHEEL
r00notify-0.1.1.dist-info/RECORD
