Metadata-Version: 2.4
Name: r00notify
Version: 0.1.1
Requires-Python: >=3.10
Requires-Dist: pytelegrambotapi
